MolTransformer/__init__.py
MolTransformer/generative/__init__.py
MolTransformer/generative/generative_method.py
MolTransformer/generative/generative_utils.py
MolTransformer/generative/settings.py
MolTransformer/model/__init__.py
MolTransformer/model/core.py
MolTransformer/model/notes.py
MolTransformer/model/model_architecture/__init__.py
MolTransformer/model/model_architecture/chem_transformer.py
MolTransformer/model/model_architecture/descriptor_hf.py
MolTransformer/model/model_architecture/high_fidelity.py
MolTransformer/model/model_architecture/low_fidelity.py
MolTransformer/model/model_architecture/mini_hf.py
MolTransformer/model/model_architecture/multi_fidelity.py
MolTransformer/model/model_architecture/positional_encoding.py
MolTransformer/model/model_architecture/settings.py
MolTransformer/model/model_operation/__init__.py
MolTransformer/model/model_operation/build_model.py
MolTransformer/model/model_operation/data_loader.py
MolTransformer/model/model_operation/operation.py
MolTransformer/model/model_operation/settings.py
MolTransformer/model/utils/__init__.py
MolTransformer/model/utils/data_processing.py
MolTransformer/model/utils/descriptors.py
MolTransformer/model/utils/distributed_utils.py
MolTransformer/model/utils/general_utils.py
MolTransformer/model/utils/loss.py
MolTransformer/model/utils/settings.py
moltransformer-0.2.1.dist-info/METADATA
moltransformer-0.2.1.dist-info/WHEEL
moltransformer-0.2.1.dist-info/top_level.txt
moltransformer-0.2.1.dist-info/RECORD
