Metadata-Version: 2.4
Name: MolTransformer
Version: 0.2.1
Summary: A python package for the paper: MolGen-Transformer: A molecule language model for the generation and latent space exploration of pi-conjugated molecules
Home-page: https://github.com/BaskarGroup/MolTransformer_repo
Author: Chih-Hsuan Yang
Author-email: chyang@iastate.edu
Classifier: Programming Language :: Python :: 3
Classifier: License :: OSI Approved :: MIT License
Classifier: Operating System :: OS Independent
Requires-Python: >=3.7
Requires-Dist: torch>=1.10
Requires-Dist: numpy>=1.19
Requires-Dist: matplotlib>=3.0
Requires-Dist: pillow>=9.0
Requires-Dist: pandas>=1.0
Requires-Dist: scikit-learn>=0.24
Requires-Dist: scipy>=1.5
Requires-Dist: selfies>=2.0
Requires-Dist: certifi>=2021.5.30
Requires-Dist: pubchempy>=1.0
Requires-Dist: hostlist
Dynamic: author
Dynamic: author-email
Dynamic: classifier
Dynamic: description-content-type
Dynamic: home-page
Dynamic: requires-dist
Dynamic: requires-python
Dynamic: summary
